food2vec/__init__.py
food2vec/semantic_nutrition.py
food2vec-0.0.4.dist-info/LICENSE.txt
food2vec-0.0.4.dist-info/METADATA
food2vec-0.0.4.dist-info/WHEEL
food2vec-0.0.4.dist-info/top_level.txt
food2vec-0.0.4.dist-info/RECORD
